image_viewer_mk2/__init__.py
image_viewer_mk2/__main__.py
image_viewer_mk2/app.py
image_viewer_mk2/model.py
image_viewer_mk2/presenter.py
image_viewer_mk2/renderer.py
image_viewer_mk2/skin.py
image_viewer_mk2/view.py
image_viewer_mk2/ObservableCollections/__init__.py
image_viewer_mk2/ObservableCollections/event.py
image_viewer_mk2/ObservableCollections/observable.py
image_viewer_mk2/ObservableCollections/observabledict.py
image_viewer_mk2/ObservableCollections/observablelist.py
image_viewer_mk2/ObservableCollections/observableset.py
image_viewer_mk2/ObservableCollections/utils.py
image_viewer_mk2/filters/__init__.py
image_viewer_mk2/filters/anisotropic_denoising.py
image_viewer_mk2/filters/filter.py
image_viewer_mk2/filters/filter_factory.py
image_viewer_mk2/filters/frangi.py
image_viewer_mk2/filters/gamma_correction.py
image_viewer_mk2/filters/gaussian_blur.py
image_viewer_mk2/filters/local_norm.py
image_viewer_mk2/filters/minmax_norm.py
image_viewer_mk2/filters/pipeline.py
image_viewer_mk2/filters/sigmoid_norm.py
image_viewer_mk2/filters/unsharp_mask.py
image_viewer_mk2/resources/arrow_down16.png
image_viewer_mk2/resources/arrow_left16.png
image_viewer_mk2/resources/color16.png
image_viewer_mk2/resources/colorpicker16.png
image_viewer_mk2/resources/copy16.png
image_viewer_mk2/resources/drag16.png
image_viewer_mk2/resources/eye16.png
image_viewer_mk2/resources/favicon.ico
image_viewer_mk2/resources/loader.gif
image_viewer_mk2/resources/logo128.png
image_viewer_mk2/resources/paste16.png
image_viewer_mk2/tk_widgets/__init__.py
image_viewer_mk2/tk_widgets/channels_list.py
image_viewer_mk2/tk_widgets/filter_config.py
image_viewer_mk2/tk_widgets/limiter.py
image_viewer_mk2/tk_widgets/link_button.py
image_viewer_mk2/tk_widgets/loader_animation.py
image_viewer_mk2/tk_widgets/panel_pipelines.py
image_viewer_mk2/tk_widgets/scrolled_frame.py
image_viewer_mk2/tk_widgets/slider.py
image_viewer_mk2/tk_widgets/sortable_accordion.py
image_viewer_mk2/tk_widgets/toggle_button.py
image_viewer_mk2-1.0.0.dist-info/LICENSE.txt
image_viewer_mk2-1.0.0.dist-info/METADATA
image_viewer_mk2-1.0.0.dist-info/WHEEL
image_viewer_mk2-1.0.0.dist-info/entry_points.txt
image_viewer_mk2-1.0.0.dist-info/top_level.txt
image_viewer_mk2-1.0.0.dist-info/RECORD
