Metadata-Version: 2.1
Name: image-viewer-mk2
Version: 1.0.0
Summary: Image viewer for spectral images
Home-page: https://github.com/jankukacka/image_viewer_mk2
Author: Jan Kukacka
License: MIT
Platform: UNKNOWN
Classifier: Programming Language :: Python :: 3
Classifier: Programming Language :: Python :: 3.7
Classifier: License :: OSI Approved :: MIT License
Classifier: Operating System :: Microsoft :: Windows
Requires-Python: >=3.7
License-File: LICENSE.txt
Requires-Dist: matplotlib
Requires-Dist: numpy
Requires-Dist: scipy
Requires-Dist: Pillow
Requires-Dist: scikit-image
Requires-Dist: happy-tools
Requires-Dist: pywin32 ; platform_system == "Windows"
Requires-Dist: jsonschema (==3.0.2) ; python_version < "3.8.0"
Requires-Dist: importlib-metadata ; python_version < "3.8.0"
